darbiadev_wolframalpha/__init__.py
darbiadev_wolframalpha/wolframalpha_services.py
darbiadev_wolframalpha-0.3.0.dist-info/LICENSE
darbiadev_wolframalpha-0.3.0.dist-info/METADATA
darbiadev_wolframalpha-0.3.0.dist-info/WHEEL
darbiadev_wolframalpha-0.3.0.dist-info/top_level.txt
darbiadev_wolframalpha-0.3.0.dist-info/RECORD
